serp_mcp/__init__.py
serp_mcp/config.py
serp_mcp/core.py
serp_mcp/mcp_server.py
serp_mcp/parser.py
serp_mcp/scraper.py
serp_mcp/types.py
serp_mcp/uule.proto
serp_mcp/uule_pb2.py
serp_mcp-0.1.8.dist-info/METADATA
serp_mcp-0.1.8.dist-info/WHEEL
serp_mcp-0.1.8.dist-info/entry_points.txt
serp_mcp-0.1.8.dist-info/licenses/LICENSE
serp_mcp-0.1.8.dist-info/RECORD
