Metadata-Version: 2.4
Name: serp-mcp
Version: 0.1.8
Summary: Google SERP MCP server with fingerprint rotation
Author: Liran Yoffe
License-Expression: MIT
License-File: LICENSE
Classifier: Development Status :: 4 - Beta
Classifier: Intended Audience :: Developers
Classifier: License :: OSI Approved :: MIT License
Classifier: Operating System :: OS Independent
Classifier: Programming Language :: Python :: 3
Classifier: Programming Language :: Python :: 3.11
Classifier: Programming Language :: Python :: 3.12
Classifier: Topic :: Internet :: WWW/HTTP :: Indexing/Search
Requires-Python: >=3.11
Requires-Dist: camoufox[geoip]
Requires-Dist: fastmcp
Requires-Dist: protobuf
Requires-Dist: pydantic
